mannarsh/__init__.py
mannarsh/main.py
mannarsh-0.1.0.dist-info/METADATA
mannarsh-0.1.0.dist-info/WHEEL
mannarsh-0.1.0.dist-info/top_level.txt
mannarsh-0.1.0.dist-info/RECORD
