Metadata-Version: 2.4
Name: mannarsh
Version: 0.1.0
Summary: A simple package providing multiplication tables up to 10
Author: Mannarsh Singh Bali
Requires-Python: >=3.8
Dynamic: author
Dynamic: requires-python
Dynamic: summary
